AUTHORS.rst
CONTRIBUTING.rst
HISTORY.rst
LICENSE
MANIFEST.in
README.rst
setup.cfg
setup.py
docs/Makefile
docs/authors.rst
docs/conf.py
docs/contributing.rst
docs/history.rst
docs/index.rst
docs/installation.rst
docs/make.bat
docs/readme.rst
docs/usage.rst
pindrop/__init__.py
pindrop/cli.py
pindrop/pindrop.py
pindrop.egg-info/PKG-INFO
pindrop.egg-info/SOURCES.txt
pindrop.egg-info/dependency_links.txt
pindrop.egg-info/entry_points.txt
pindrop.egg-info/not-zip-safe
pindrop.egg-info/requires.txt
pindrop.egg-info/top_level.txt
tests/__init__.py
tests/test_pindrop.py