Metadata-Version: 1.1
Name: pindrop
Version: 0.1.0
Summary: A python package that creates the models, the urls, the filters, the pagination, the database and returns GeoJSON for the pindrops and returns JSON for the other models. 
Home-page: https://github.com/MisaelMvM/pindrop
Author: Misael Virissimo de Moura
Author-email: mvmmisael@gmail.com
License: MIT license
Keywords: pindrop
Platform: UNKNOWN
Classifier: Development Status :: 2 - Pre-Alpha
Classifier: Intended Audience :: Developers
Classifier: License :: OSI Approved :: MIT License
Classifier: Natural Language :: English
Classifier: Programming Language :: Python :: 2
Classifier: Programming Language :: Python :: 2.6
Classifier: Programming Language :: Python :: 2.7
Classifier: Programming Language :: Python :: 3
Classifier: Programming Language :: Python :: 3.3
Classifier: Programming Language :: Python :: 3.4
Classifier: Programming Language :: Python :: 3.5
